{"currencyCode":"HKD","trips":[{"tripNumber":0,"flights":[{"segments":[{"flightNumber":"UO848","departureStationCode":"HKG","arrivalTerminal":"2","departureTerminal":"2","departureDate":"2019-01-01T09:20:00","departureDateUtc":"2019-01-01T01:20:00Z","arrivalStationCode":"NRT","arrivalDate":"2019-01-01T14:25:00","arrivalDateUtc":"2019-01-01T05:25:00Z","flightTime":"04:05:00","segmentId":"554F7E203834387E207E7E484B477E30312F30312F323031392030393A32307E4E52547E30312F30312F323031392031343A32357E","subjectToGovtApproval":false}],"fares":[{"passengerType":"ADT","productClass":"F1","amount":1238.0000,"fareId":"0~X~~XF1R~9000~~14~X","taxes":[],"discounts":[]},{"passengerType":"ADT","productClass":"F3","amount":1668.0000,"fareId":"0~X~~XF3R~9020~~3~X","taxes":[],"discounts":[]},{"passengerType":"ADT","productClass":"F4","amount":2028.0000,"fareId":"0~X~~XF4R~901A~~3~X","taxes":[],"discounts":[]}],"sellKey":"554F7E203834387E207E7E484B477E30312F30312F323031392030393A32307E4E52547E30312F30312F323031392031343A32357E","isThereInfantCapacity":true},{"segments":[{"flightNumber":"UO870","departureStationCode":"HKG","arrivalTerminal":"2","departureTerminal":"2","departureDate":"2019-01-01T10:50:00","departureDateUtc":"2019-01-01T02:50:00Z","arrivalStationCode":"NRT","arrivalDate":"2019-01-01T16:00:00","arrivalDateUtc":"2019-01-01T07:00:00Z","flightTime":"04:10:00","segmentId":"554F7E203837307E207E7E484B477E30312F30312F323031392031303A35307E4E52547E30312F30312F323031392031363A30307E","subjectToGovtApproval":false}],"fares":[{"passengerType":"ADT","productClass":"F1","amount":1088.0000,"fareId":"0~Q~~QF1R~9000~~16~X","taxes":[],"discounts":[]},{"passengerType":"ADT","productClass":"F3","amount":1518.0000,"fareId":"0~Q~~QF3R~9020~~3~X","taxes":[],"discounts":[]},{"passengerType":"ADT","productClass":"F4","amount":1878.0000,"fareId":"0~Q~~QF4R~901A~~3~X","taxes":[],"discounts":[]}],"sellKey":"554F7E203837307E207E7E484B477E30312F30312F323031392031303A35307E4E52547E30312F30312F323031392031363A30307E","isThereInfantCapacity":true},{"segments":[{"flightNumber":"UO646","departureStationCode":"HKG","arrivalTerminal":"2","departureTerminal":"2","departureDate":"2019-01-01T13:00:00","departureDateUtc":"2019-01-01T05:00:00Z","arrivalStationCode":"NRT","arrivalDate":"2019-01-01T18:05:00","arrivalDateUtc":"2019-01-01T09:05:00Z","flightTime":"04:05:00","segmentId":"554F7E203634367E207E7E484B477E30312F30312F323031392031333A30307E4E52547E30312F30312F323031392031383A30357E","subjectToGovtApproval":false}],"fares":[{"passengerType":"ADT","productClass":"F1","amount":1088.0000,"fareId":"0~Q~~QF1R~9000~~16~X","taxes":[],"discounts":[]},{"passengerType":"ADT","productClass":"F3","amount":1518.0000,"fareId":"0~Q~~QF3R~9020~~3~X","taxes":[],"discounts":[]},{"passengerType":"ADT","productClass":"F4","amount":1878.0000,"fareId":"0~Q~~QF4R~901A~~3~X","taxes":[],"discounts":[]}],"sellKey":"554F7E203634367E207E7E484B477E30312F30312F323031392031333A30307E4E52547E30312F30312F323031392031383A30357E","isThereInfantCapacity":true},{"segments":[{"flightNumber":"UO650","departureStationCode":"HKG","arrivalTerminal":"2","departureTerminal":"2","departureDate":"2019-01-01T14:00:00","departureDateUtc":"2019-01-01T06:00:00Z","arrivalStationCode":"NRT","arrivalDate":"2019-01-01T19:05:00","arrivalDateUtc":"2019-01-01T10:05:00Z","flightTime":"04:05:00","segmentId":"554F7E203635307E207E7E484B477E30312F30312F323031392031343A30307E4E52547E30312F30312F323031392031393A30357E","subjectToGovtApproval":false}],"fares":[{"passengerType":"ADT","productClass":"F1","amount":1088.0000,"fareId":"0~Q~~QF1R~9000~~16~X","taxes":[],"discounts":[]},{"passengerType":"ADT","productClass":"F3","amount":1518.0000,"fareId":"0~Q~~QF3R~9020~~3~X","taxes":[],"discounts":[]},{"passengerType":"ADT","productClass":"F4","amount":1878.0000,"fareId":"0~Q~~QF4R~901A~~3~X","taxes":[],"discounts":[]}],"sellKey":"554F7E203635307E207E7E484B477E30312F30312F323031392031343A30307E4E52547E30312F30312F323031392031393A30357E","isThereInfantCapacity":true},{"segments":[{"flightNumber":"UO32","departureStationCode":"HKG","arrivalTerminal":"I","departureTerminal":"2","departureDate":"2019-01-01T18:00:00","departureDateUtc":"2019-01-01T10:00:00Z","arrivalStationCode":"HND","arrivalDate":"2019-01-01T22:55:00","arrivalDateUtc":"2019-01-01T13:55:00Z","flightTime":"03:55:00","segmentId":"554F7E202033327E207E7E484B477E30312F30312F323031392031383A30307E484E447E30312F30312F323031392032323A35357E","subjectToGovtApproval":false}],"fares":[{"passengerType":"ADT","productClass":"F1","amount":1088.0000,"fareId":"0~Q~~QF1R~9000~~16~X","taxes":[],"discounts":[]},{"passengerType":"ADT","productClass":"F3","amount":1518.0000,"fareId":"0~Q~~QF3R~9020~~3~X","taxes":[],"discounts":[]},{"passengerType":"ADT","productClass":"F4","amount":1878.0000,"fareId":"0~Q~~QF4R~901A~~3~X","taxes":[],"discounts":[]}],"sellKey":"554F7E202033327E207E7E484B477E30312F30312F323031392031383A30307E484E447E30312F30312F323031392032323A35357E","isThereInfantCapacity":true},{"segments":[{"flightNumber":"UO624","departureStationCode":"HKG","arrivalTerminal":"I","departureTerminal":"2","departureDate":"2019-01-01T23:50:00","departureDateUtc":"2019-01-01T15:50:00Z","arrivalStationCode":"HND","arrivalDate":"2019-01-02T04:45:00","arrivalDateUtc":"2019-01-01T19:45:00Z","flightTime":"03:55:00","segmentId":"554F7E203632347E207E7E484B477E30312F30312F323031392032333A35307E484E447E30312F30322F323031392030343A34357E","subjectToGovtApproval":false}],"fares":[{"passengerType":"ADT","productClass":"F1","amount":1238.0000,"fareId":"0~X~~XF1R~9000~~14~X","taxes":[],"discounts":[]},{"passengerType":"ADT","productClass":"F3","amount":1668.0000,"fareId":"0~X~~XF3R~9020~~3~X","taxes":[],"discounts":[]},{"passengerType":"ADT","productClass":"F4","amount":2028.0000,"fareId":"0~X~~XF4R~901A~~3~X","taxes":[],"discounts":[]}],"sellKey":"554F7E203632347E207E7E484B477E30312F30312F323031392032333A35307E484E447E30312F30322F323031392030343A34357E","isThereInfantCapacity":true}]},{"tripNumber":1,"flights":[{"segments":[{"flightNumber":"UO625","departureStationCode":"HND","arrivalTerminal":"1","departureTerminal":"I","departureDate":"2019-01-08T06:25:00","departureDateUtc":"2019-01-07T21:25:00Z","arrivalStationCode":"HKG","arrivalDate":"2019-01-08T10:45:00","arrivalDateUtc":"2019-01-08T02:45:00Z","flightTime":"05:20:00","segmentId":"554F7E203632357E207E7E484E447E30312F30382F323031392030363A32357E484B477E30312F30382F323031392031303A34357E","subjectToGovtApproval":false}],"fares":[{"passengerType":"ADT","productClass":"F1","amount":1088.0000,"fareId":"0~Q~~QF1R~9000~~16~X","taxes":[],"discounts":[]},{"passengerType":"ADT","productClass":"F3","amount":1518.0000,"fareId":"0~Q~~QF3R~9020~~3~X","taxes":[],"discounts":[]},{"passengerType":"ADT","productClass":"F4","amount":1878.0000,"fareId":"0~Q~~QF4R~901A~~3~X","taxes":[],"discounts":[]}],"sellKey":"554F7E203632357E207E7E484E447E30312F30382F323031392030363A32357E484B477E30312F30382F323031392031303A34357E","isThereInfantCapacity":true},{"segments":[{"flightNumber":"UO849","departureStationCode":"NRT","arrivalTerminal":"1","departureTerminal":"2","departureDate":"2019-01-08T15:20:00","departureDateUtc":"2019-01-08T06:20:00Z","arrivalStationCode":"HKG","arrivalDate":"2019-01-08T20:00:00","arrivalDateUtc":"2019-01-08T12:00:00Z","flightTime":"05:40:00","segmentId":"554F7E203834397E207E7E4E52547E30312F30382F323031392031353A32307E484B477E30312F30382F323031392032303A30307E","subjectToGovtApproval":false}],"fares":[{"passengerType":"ADT","productClass":"F1","amount":1378.0000,"fareId":"0~S~~SF1R~9000~~14~X","taxes":[],"discounts":[]},{"passengerType":"ADT","productClass":"F3","amount":1808.0000,"fareId":"0~S~~SF3R~9020~~3~X","taxes":[],"discounts":[]},{"passengerType":"ADT","productClass":"F4","amount":2168.0000,"fareId":"0~S~~SF4R~901A~~3~X","taxes":[],"discounts":[]}],"sellKey":"554F7E203834397E207E7E4E52547E30312F30382F323031392031353A32307E484B477E30312F30382F323031392032303A30307E","isThereInfantCapacity":true},{"segments":[{"flightNumber":"UO871","departureStationCode":"NRT","arrivalTerminal":"1","departureTerminal":"2","departureDate":"2019-01-08T17:00:00","departureDateUtc":"2019-01-08T08:00:00Z","arrivalStationCode":"HKG","arrivalDate":"2019-01-08T21:40:00","arrivalDateUtc":"2019-01-08T13:40:00Z","flightTime":"05:40:00","segmentId":"554F7E203837317E207E7E4E52547E30312F30382F323031392031373A30307E484B477E30312F30382F323031392032313A34307E","subjectToGovtApproval":false}],"fares":[{"passengerType":"ADT","productClass":"F1","amount":1378.0000,"fareId":"0~S~~SF1R~9000~~14~X","taxes":[],"discounts":[]},{"passengerType":"ADT","productClass":"F3","amount":1808.0000,"fareId":"0~S~~SF3R~9020~~3~X","taxes":[],"discounts":[]},{"passengerType":"ADT","productClass":"F4","amount":2168.0000,"fareId":"0~S~~SF4R~901A~~3~X","taxes":[],"discounts":[]}],"sellKey":"554F7E203837317E207E7E4E52547E30312F30382F323031392031373A30307E484B477E30312F30382F323031392032313A34307E","isThereInfantCapacity":true},{"segments":[{"flightNumber":"UO647","departureStationCode":"NRT","arrivalTerminal":"1","departureTerminal":"2","departureDate":"2019-01-08T19:00:00","departureDateUtc":"2019-01-08T10:00:00Z","arrivalStationCode":"HKG","arrivalDate":"2019-01-08T23:40:00","arrivalDateUtc":"2019-01-08T15:40:00Z","flightTime":"05:40:00","segmentId":"554F7E203634377E207E7E4E52547E30312F30382F323031392031393A30307E484B477E30312F30382F323031392032333A34307E","subjectToGovtApproval":false}],"fares":[{"passengerType":"ADT","productClass":"F1","amount":1088.0000,"fareId":"0~Q~~QF1R~9000~~16~X","taxes":[],"discounts":[]},{"passengerType":"ADT","productClass":"F3","amount":1518.0000,"fareId":"0~Q~~QF3R~9020~~3~X","taxes":[],"discounts":[]},{"passengerType":"ADT","productClass":"F4","amount":1878.0000,"fareId":"0~Q~~QF4R~901A~~3~X","taxes":[],"discounts":[]}],"sellKey":"554F7E203634377E207E7E4E52547E30312F30382F323031392031393A30307E484B477E30312F30382F323031392032333A34307E","isThereInfantCapacity":true},{"segments":[{"flightNumber":"UO651","departureStationCode":"NRT","arrivalTerminal":"1","departureTerminal":"2","departureDate":"2019-01-08T20:00:00","departureDateUtc":"2019-01-08T11:00:00Z","arrivalStationCode":"HKG","arrivalDate":"2019-01-09T00:40:00","arrivalDateUtc":"2019-01-08T16:40:00Z","flightTime":"05:40:00","segmentId":"554F7E203635317E207E7E4E52547E30312F30382F323031392032303A30307E484B477E30312F30392F323031392030303A34307E","subjectToGovtApproval":false}],"fares":[{"passengerType":"ADT","productClass":"F1","amount":1088.0000,"fareId":"0~Q~~QF1R~9000~~16~X","taxes":[],"discounts":[]},{"passengerType":"ADT","productClass":"F3","amount":1518.0000,"fareId":"0~Q~~QF3R~9020~~3~X","taxes":[],"discounts":[]},{"passengerType":"ADT","productClass":"F4","amount":1878.0000,"fareId":"0~Q~~QF4R~901A~~3~X","taxes":[],"discounts":[]}],"sellKey":"554F7E203635317E207E7E4E52547E30312F30382F323031392032303A30307E484B477E30312F30392F323031392030303A34307E","isThereInfantCapacity":true},{"segments":[{"flightNumber":"UO33","departureStationCode":"HND","arrivalTerminal":"1","departureTerminal":"I","departureDate":"2019-01-08T23:55:00","departureDateUtc":"2019-01-08T14:55:00Z","arrivalStationCode":"HKG","arrivalDate":"2019-01-09T04:15:00","arrivalDateUtc":"2019-01-08T20:15:00Z","flightTime":"05:20:00","segmentId":"554F7E202033337E207E7E484E447E30312F30382F323031392032333A35357E484B477E30312F30392F323031392030343A31357E","subjectToGovtApproval":false}],"fares":[{"passengerType":"ADT","productClass":"F1","amount":1528.0000,"fareId":"0~N~~NF1R~9000~~14~X","taxes":[],"discounts":[]},{"passengerType":"ADT","productClass":"F3","amount":1958.0000,"fareId":"0~N~~NF3R~9020~~3~X","taxes":[],"discounts":[]},{"passengerType":"ADT","productClass":"F4","amount":2318.0000,"fareId":"0~N~~NF4R~901A~~3~X","taxes":[],"discounts":[]}],"sellKey":"554F7E202033337E207E7E484E447E30312F30382F323031392032333A35357E484B477E30312F30392F323031392030343A31357E","isThereInfantCapacity":true}]}],"success":true,"errors":[]}
